{
  "actors": [
    "Liat",
    "???"
  ],
  "decks": [
    {
      "speaker": "Liat",
      "cards": [
        {
          "lines": [
            "Citizen, are you home?",
            "We need help!"
          ],
          "emotionalResponses": {
            "Liat": {
              "position": 0,
              "facing": "left",
              "emotion": "default"
            },
            "???": {
              "position": 1,
              "facing": "left",
              "emotion": "default"
            }
          }
        }
      ]
    },
    {
      "speaker": "???",
      "cards": [
        {
          "lines": [
            "..."
          ],
          "emotionalResponses": {
            "Liat": {
              "position": 0,
              "facing": "left",
              "emotion": "default"
            },
            "???": {
              "position": 1,
              "facing": "left",
              "emotion": "default"
            }
          }
        }
      ]
    },
    {
      "speaker": "Liat",
      "cards": [
        {
          "lines": [
            "Hello?"
          ],
          "emotionalResponses": {
            "Liat": {
              "position": 0,
              "facing": "left",
              "emotion": "default"
            },
            "???": {
              "position": 1,
              "facing": "left",
              "emotion": "default"
            }
          }
        }
      ]
    },
    {
      "speaker": "???",
      "cards": [
        {
          "lines": [
            "... we've paid you already!",
            "Please, we don't have anything of value!"
          ],
          "emotionalResponses": {
            "Liat": {
              "position": 0,
              "facing": "left",
              "emotion": "default"
            },
            "???": {
              "position": 1,
              "facing": "left",
              "emotion": "default"
            }
          }
        }
      ]
    },
    {
      "speaker": "Liat",
      "cards": [
        {
          "lines": [
            "Value?",
            "I don't want your money..."
          ],
          "emotionalResponses": {
            "Liat": {
              "position": 0,
              "facing": "left",
              "emotion": "default"
            },
            "???": {
              "position": 1,
              "facing": "left",
              "emotion": "default"
            }
          }
        }
      ]
    }
  ]
}